salmon/__init__.py
salmon/urls.py
salmon/wsgi.py
salmon/core/__init__.py
salmon/core/authentication.py
salmon/core/graph.py
salmon/core/permissions.py
salmon/core/runner.py
salmon/core/server.py
salmon/core/management/__init__.py
salmon/core/management/commands/__init__.py
salmon/core/management/commands/start.py
salmon/core/management/commands/upgrade.py
salmon/core/tests/__init__.py
salmon/core/tests/test_authentication.py
salmon/core/tests/test_graph.py
salmon/metrics/__init__.py
salmon/metrics/admin.py
salmon/metrics/forms.py
salmon/metrics/models.py
salmon/metrics/serializers.py
salmon/metrics/utils.py
salmon/metrics/views.py
salmon/metrics/management/__init__.py
salmon/metrics/management/commands/__init__.py
salmon/metrics/management/commands/generate_sample_data.py
salmon/metrics/migrations/0001_initial.py
salmon/metrics/migrations/0002_auto__add_field_metric_is_counter.py
salmon/metrics/migrations/0003_auto__add_field_metric_transform.py
salmon/metrics/migrations/0004_auto__add_field_metric__previous_counter_value.py
salmon/metrics/migrations/__init__.py
salmon/metrics/templatetags/__init__.py
salmon/metrics/templatetags/metrics.py
salmon/metrics/tests/__init__.py
salmon/metrics/tests/test_models.py
salmon/metrics/tests/test_serializers.py
salmon/metrics/tests/test_utils.py
salmon/metrics/tests/test_views.py
salmon/settings/__init__.py
salmon/settings/base.py
salmon/settings/local.py
salmon/settings/example/conf.py
salmon/static/.DS_Store
salmon/static/favicon.ico
salmon/static/css/bootstrap-datetimepicker.min.css
salmon/static/css/bootstrap.min.css
salmon/static/fonts/glyphicons-halflings-regular.eot
salmon/static/fonts/glyphicons-halflings-regular.svg
salmon/static/fonts/glyphicons-halflings-regular.ttf
salmon/static/fonts/glyphicons-halflings-regular.woff
salmon/static/img/glyphicons-halflings-white.png
salmon/static/img/glyphicons-halflings.png
salmon/static/img/salmon.png
salmon/static/js/app/app.js
salmon-0.2.0.dist-info/DESCRIPTION.rst
salmon-0.2.0.dist-info/entry_points.txt
salmon-0.2.0.dist-info/METADATA
salmon-0.2.0.dist-info/pydist.json
salmon-0.2.0.dist-info/RECORD
salmon-0.2.0.dist-info/top_level.txt
salmon-0.2.0.dist-info/WHEEL
