Metadata-Version: 2.0
Name: salmon
Version: 0.2.0
Summary: A simple metric collector with alerts.
Home-page: https://github.com/lincolnloop/salmon
Author: Peter Baumgarter
Author-email: pete@lincolnloop.com
License: BSD
Platform: UNKNOWN
Requires-Dist: django (==1.6.1)
Requires-Dist: djangorestframework (==2.3.9)
Requires-Dist: South (==0.8.3)
Requires-Dist: logan (==0.5.9.1)
Requires-Dist: gunicorn (==18.0)
Requires-Dist: whisper (==0.9.10)
Requires-Dist: dj-static (==0.0.5)
Requires-Dist: pytz
